mkm/__init__.py
mkm/address.py
mkm/identifier.py
mkm/crypto/__init__.py
mkm/crypto/asymmetric.py
mkm/crypto/cryptography.py
mkm/crypto/digest.py
mkm/crypto/helpers.py
mkm/crypto/private.py
mkm/crypto/public.py
mkm/crypto/symmetric.py
mkm/ext/__init__.py
mkm/ext/account.py
mkm/ext/crypto.py
mkm/ext/format.py
mkm/format/__init__.py
mkm/format/data.py
mkm/format/encode.py
mkm/format/file.py
mkm/format/helpers.py
mkm/format/object.py
mkm/format/string.py
mkm/protocol/__init__.py
mkm/protocol/address.py
mkm/protocol/entity.py
mkm/protocol/helpers.py
mkm/protocol/identifier.py
mkm/protocol/meta.py
mkm/protocol/tai.py
mkm/protocol/tai_doc.py
mkm/types/__init__.py
mkm/types/converter.py
mkm/types/copier.py
mkm/types/dictionary.py
mkm/types/string.py
mkm/types/wrapper.py
mkm/types/x.py
mkm-2.3.4.dist-info/LICENSE
mkm-2.3.4.dist-info/METADATA
mkm-2.3.4.dist-info/WHEEL
mkm-2.3.4.dist-info/top_level.txt
mkm-2.3.4.dist-info/RECORD
