Metadata-Version: 2.1
Name: mkm
Version: 2.3.4
Summary: A common identity module
Home-page: https://github.com/dimchat/mkm-py
Author: Albert Moky
Author-email: albert.moky@gmail.com
License: MIT
Classifier: Programming Language :: Python :: 3
Classifier: License :: OSI Approved :: MIT License
Classifier: Operating System :: OS Independent
License-File: LICENSE
